LICENSE
MANIFEST.in
README.md
pyproject.toml
requirements.txt
requirements_test.txt
setup.py
pyusblamp/__init__.py
pyusblamp/applog.py
pyusblamp/imap2usblamp.py
pyusblamp/oauth2.py
pyusblamp/pyusblamp.py
pyusblamp.egg-info/PKG-INFO
pyusblamp.egg-info/SOURCES.txt
pyusblamp.egg-info/dependency_links.txt
pyusblamp.egg-info/entry_points.txt
pyusblamp.egg-info/requires.txt
pyusblamp.egg-info/top_level.txt
pyusblamp/libusb/README.md
pyusblamp/libusb/MS32/dll/libusb-1.0.dll
pyusblamp/libusb/MS32/dll/libusb-1.0.lib
pyusblamp/libusb/MS32/dll/libusb-1.0.pdb
pyusblamp/libusb/MS64/dll/libusb-1.0.dll
pyusblamp/libusb/MS64/dll/libusb-1.0.lib
pyusblamp/libusb/MS64/dll/libusb-1.0.pdb
tests/__init__.py
tests/test_pyusblamp.py