Metadata-Version: 2.1
Name: pyusblamp
Version: 1.41
Summary: Mailbox Friends Alert (Dream Cheeky) Driver
Home-page: https://github.com/onelife/PyUsbLamp
Download-URL: https://github.com/onelife/PyUsbLamp/archive/1.41.tar.gz
Author: onelife
Author-email: onelife.real@gmail.com
License: GPLv3
Keywords: usblamp,usb,lamp,mailbox,alert,driver
Classifier: Environment :: Console
Classifier: License :: OSI Approved :: GNU General Public License v3 or later (GPLv3+)
Classifier: Natural Language :: English
Classifier: Operating System :: Microsoft :: Windows
Classifier: Operating System :: POSIX :: Linux
Classifier: Programming Language :: Python :: 3.10
Classifier: Topic :: System :: Hardware :: Hardware Drivers
Provides-Extra: test
License-File: LICENSE
